{
    "wallet_address": "0x123...",
    "transactions": [
        {
            "id": "tx1",
            "amount": 100,
            "counterparty": "0xabc",
            "success": true
        },
        {
            "id": "tx2",
            "amount": 200,
            "counterparty": "0xdef",
            "success": true
        }
    ],
    "contracts": [
        "contract1",
        "contract2"
    ],
    "governance_events": [
        {
            "event": "vote",
            "timestamp": "2024-01-01"
        }
    ]
}